{
    "ProductName": "be quiet! Light Wings 120mm PWM",
    "DisplayName": "be quiet! Light Wings 120mm PWM - 18 LED",
    "Brand" : "be quiet!",
    "Type" : "Fan",
    "LedCount" : 18,
    "Width": 10,
    "Height": 10,
    "LedMapping" : [
                15,16, 17,0,
            14,             1,
           13,                2,
        12,                   3,
         11,                 4,
             10,          5,
                   9,8,7,6
        ],
    "LedCoordinates" : [
                [3,1],[4,0], [5,0],  [6,1],
           [2,2],                        [7,2],
		[1,3],                             [8,3],
        [0,4],                              [9,4],
         [1,5],                           [8,5],
		   [2,6],                       [7,6],
                [3,7],[4,8],[5,8],[6,7]
    ],
    "LedNames" : [
        "Led 1","Led 2","Led 3","Led 4","Led 5","Led 6","Led 7","Led 8","Led 9","Led 10","Led11","Led 12","Led 13","Led 14","Led 15","Led 16","Led 17","Led 18"
    ],
    "Image": ""
}
